setup.py
essun_test.egg-info/PKG-INFO
essun_test.egg-info/SOURCES.txt
essun_test.egg-info/dependency_links.txt
essun_test.egg-info/requires.txt
essun_test.egg-info/top_level.txt
mm/__init__.py
mm/test.py