Metadata-Version: 1.0
Name: essun-test
Version: 0.0.1
Summary: a description test framework
Home-page: http://www.google.com
Author: Kinggp
Author-email: jinlinger.love@163.com
License: MIT
Keywords: framework nose testing
Platform: any
